isotel/__init__.py
isotel/IoT/IoT.py
isotel/IoT/IoTProtocol.py
isotel/IoT/IoTService.py
isotel/IoT/IoTurllib2.py
isotel/IoT/IoTurllib3.py
isotel/IoT/__init__.py
isotel/IoT/_version.py
isotel_iot-1.3.64.dist-info/DESCRIPTION.rst
isotel_iot-1.3.64.dist-info/METADATA
isotel_iot-1.3.64.dist-info/RECORD
isotel_iot-1.3.64.dist-info/WHEEL
isotel_iot-1.3.64.dist-info/metadata.json
isotel_iot-1.3.64.dist-info/top_level.txt
