Metadata-Version: 2.0
Name: isotel-iot
Version: 1.3.64
Summary: An API interface to communicate with an ISOTEL of Things (IoT) server, used to manage hardware devices like sensors, actuators, etc.
Home-page: http://www.isotel.eu/IoT
Author: Tine Kavcic, Uros Platise, Jayesh Bhoot
Author-email: pypi@isotel.eu
License: MIT
Keywords: internet web things heterogeneous scalable sensors hardware devices DIY
Platform: UNKNOWN
Classifier: Development Status :: 5 - Production/Stable
Classifier: Intended Audience :: Developers
Classifier: Topic :: Software Development :: Build Tools
Classifier: License :: OSI Approved :: MIT License
Classifier: Programming Language :: Python :: 2
Classifier: Programming Language :: Python :: 2.7
Classifier: Programming Language :: Python :: 3
Classifier: Programming Language :: Python :: 3.3
Classifier: Programming Language :: Python :: 3.4
Classifier: Programming Language :: Python :: 3.5
